{"content":[{"id":"619673e3","settings":{"layout":"full_width","stretch_section":"section-stretched","structure":"20"},"elements":[{"id":"5a3e6a34","settings":{"_column_size":50,"_inline_size":null,"_inline_size_tablet":100,"margin":{"unit":"px","top":"0","right":"0","bottom":"0","left":"0","isLinked":false},"padding":{"unit":"px","top":"0","right":"0","bottom":"0","left":"0","isLinked":false}},"elements":[{"id":"73a98d85","settings":{"youtube_url":"https:\/\/www.youtube.com\/watch?time_continue=2&v=KTtGOvbxuj0&feature=emb_logo","vimeo_url":"https:\/\/vimeo.com\/235215203","dailymotion_url":"https:\/\/www.dailymotion.com\/video\/x6tqhqb","aspect_ratio":"32"},"elements":[],"isInner":false,"widgetType":"video","elType":"widget"}],"isInner":false,"elType":"column"},{"id":"16ed9c59","settings":{"_column_size":50,"_inline_size":null,"_inline_size_tablet":100,"content_position":"center","background_background":"classic","background_color":"#2A2A2A","margin":{"unit":"px","top":"0","right":"0","bottom":"0","left":"0","isLinked":false},"padding":{"unit":"px","top":"40","right":"15","bottom":"40","left":"15","isLinked":false}},"elements":[{"id":"3fe33b44","settings":{"main_title":"Why us ?","section_title_typography_typography":"custom","section_title_typography_font_weight":"700","section_title_typography_line_height":{"unit":"px","size":28,"sizes":[]},"main_title_el_color":"#FFFFFF","_margin":{"unit":"px","top":"0","right":"0","bottom":"0","left":"0","isLinked":false},"_padding":{"unit":"px","top":"0","right":"0","bottom":"0","left":"0","isLinked":false}},"elements":[],"isInner":false,"widgetType":"pgscore_section-title","elType":"widget"},{"id":"c35cde0","settings":{"main_title":"Because Style Matters","main_title_el":"h5","main_title_el_color":"#FFFFFF","sub_title_color":"#FFFFFF","section_description":"It is a long established fact that a reader will be distracted by the readable content of a page when looking at its layout. The point of using Lorem Ipsum is that it has a more-or-less normal distribution of letters, as opposed to using \u2018Content here, content here\u2019, making it look like readable English.","section_description_color":"#FFFFFF","_margin":{"unit":"px","top":"0","right":"0","bottom":"0","left":"0","isLinked":false},"_padding":{"unit":"px","top":"0","right":"70","bottom":"0","left":"70","isLinked":false},"_padding_mobile":{"unit":"px","top":"0","right":"0","bottom":"0","left":"0","isLinked":false}},"elements":[],"isInner":false,"widgetType":"pgscore_section-title","elType":"widget"}],"isInner":false,"elType":"column"}],"isInner":false,"elType":"section"}],"page_settings":[],"version":"0.4","title":"video-with-content","type":"section"}