{"content":[{"id":"4ef1d67b","settings":{"layout":"full_width","stretch_section":"section-stretched"},"elements":[{"id":"28bd7c8f","settings":{"_column_size":100,"_inline_size":null,"padding":{"unit":"px","top":"0","right":"0","bottom":"0","left":"0","isLinked":false}},"elements":[{"id":"ea2c052","settings":{"layout":"full_width"},"elements":[{"id":"7d7e76b1","settings":{"_column_size":100,"_inline_size":null,"padding":{"unit":"px","top":"0","right":"0","bottom":"0","left":"0","isLinked":false}},"elements":[{"id":"2cfd5ee7","settings":{"image":{"id":39854,"url":"https:\/\/ciyashop.potenzaglobalsolutions.com\/elementor\/wp-content\/uploads\/sites\/94\/2021\/01\/spice-store-bg-img.jpg","alt":"","source":"library"},"image_size":"full"},"elements":[],"isInner":false,"widgetType":"image","elType":"widget"}],"isInner":true,"elType":"column"}],"isInner":true,"elType":"section"},{"id":"48f9f01c","settings":{"margin":{"unit":"px","top":"-300","right":0,"bottom":"0","left":0,"isLinked":false},"margin_tablet":{"unit":"px","top":"-120","right":0,"bottom":"0","left":0,"isLinked":false},"margin_mobile":{"unit":"px","top":"-50","right":0,"bottom":"0","left":0,"isLinked":false},"padding":{"unit":"px","top":"0","right":"15","bottom":"0","left":"15","isLinked":false}},"elements":[{"id":"500b96fa","settings":{"_column_size":100,"_inline_size":null,"padding":{"unit":"px","top":"0","right":"0","bottom":"0","left":"0","isLinked":false}},"elements":[{"id":"c5e08c9","settings":{"bg_img_source":"external_link","bg_img_link":{"url":"https:\/\/ciyashop.potenzaglobalsolutions.com\/spice-store\/wp-content\/uploads\/sites\/24\/2018\/05\/04-1.png","is_external":false,"nofollow":false,"custom_attributes":""},"vertical_align":"vmiddle","banner_css":{"unit":"px","top":"25","right":"25","bottom":"25","left":"65","isLinked":false},"banner_enable_button":"yes","list_items":[{"title":"Fresh spice","_id":"2d8740f","color":"#323232","item_typography_typography":"custom","item_typography_font_family":"Open Sans","item_typography_font_size":{"unit":"px","size":20,"sizes":[]},"item_typography_line_height":{"unit":"px","size":30,"sizes":[]}},{"title":"Organic Foods 50% off","color":"#F35A0E","item_typography_typography":"custom","item_typography_font_family":"Damion","item_typography_font_size":{"unit":"px","size":56,"sizes":[]},"item_typography_font_weight":"100","item_typography_line_height":{"unit":"px","size":76,"sizes":[]},"_id":"c17146c","item_typography_font_size_mobile":{"unit":"px","size":26,"sizes":[]},"item_typography_line_height_mobile":{"unit":"px","size":42,"sizes":[]}},{"title":"Get 30% off on Your Order","color":"#323232","item_typography_typography":"custom","item_typography_font_family":"Open Sans","item_typography_font_size":{"unit":"px","size":28,"sizes":[]},"item_typography_line_height":{"unit":"px","size":38,"sizes":[]},"_id":"766a3a9","item_typography_font_size_mobile":{"unit":"px","size":16,"sizes":[]},"item_typography_line_height_mobile":{"unit":"px","size":26,"sizes":[]},"item_padding":{"unit":"px","top":"0","right":"0","bottom":"30","left":"0","isLinked":false}}],"button_text":"Shop Now","button_style":"flat","button_typography_typography":"custom","button_typography_font_family":"Open Sans","button_text_color":"#FFFFFF","button_background_color":"#F35A0E","button_text_hover_color":"#FFFFFF","button_background_hover_color":"#323232","button_border_radius":{"unit":"px","top":"3","right":"3","bottom":"3","left":"3","isLinked":true},"badge_title":"Lorem Ipsum","deal_expire_message":"This offer has expired.","_background_background":"classic","_background_color":"#FFFFFF","banner_css_tablet":{"unit":"px","top":"50","right":"50","bottom":"50","left":"50","isLinked":false},"banner_css_mobile":{"unit":"px","top":"20","right":"20","bottom":"20","left":"20","isLinked":true},"_margin_tablet":{"unit":"px","top":"0","right":"0","bottom":"60","left":"0","isLinked":false},"style":"deal-1","banner_enable_badge":"","deal_date":"2023-12-05 12:00","deal_padding":{"unit":"px","top":"0","right":"0","bottom":"20","left":"0","isLinked":false},"deal_counter_style":"style-8","bg_img":{"id":39853,"url":"https:\/\/ciyashop.potenzaglobalsolutions.com\/elementor\/wp-content\/uploads\/sites\/94\/2021\/01\/spice-store-bg-img.jpg"},"_box_shadow_box_shadow_type":"yes","_box_shadow_box_shadow":{"horizontal":0,"vertical":10,"blur":40,"spread":0,"color":"rgba(0, 0, 0, 0.07)"}},"elements":[],"isInner":false,"widgetType":"pgscore_banner","elType":"widget"}],"isInner":true,"elType":"column"}],"isInner":true,"elType":"section"}],"isInner":false,"elType":"column"}],"isInner":false,"elType":"section"}],"page_settings":[],"version":"0.4","title":"Product Deal Style 8 New 2","type":"section"}
