{"content":[{"id":"30f849ca","settings":{"stretch_section":"section-stretched","padding":{"unit":"px","top":"80","right":"0","bottom":"50","left":"0","isLinked":false},"margin_tablet":{"unit":"px","top":"0","right":0,"bottom":"50","left":0,"isLinked":false},"padding_tablet":{"unit":"px","top":"50","right":"0","bottom":"0","left":"0","isLinked":false},"padding_mobile":{"unit":"px","top":"40","right":"0","bottom":"0","left":"0","isLinked":false}},"elements":[{"id":"554495de","settings":{"_column_size":100,"_inline_size":null,"padding":{"unit":"px","top":"0","right":"15","bottom":"0","left":"15","isLinked":false}},"elements":[{"id":"390235a0","settings":{"section_title_style":"style-3","main_title":"Today Special","main_title_el":"h2"},"elements":[],"isInner":false,"widgetType":"pgscore_section-title","elType":"widget"},{"id":"703acab9","settings":{"structure":"20","margin":{"unit":"px","top":"30","right":0,"bottom":"0","left":0,"isLinked":false}},"elements":[{"id":"79065f0f","settings":{"_column_size":50,"_inline_size":null,"padding":{"unit":"px","top":"0","right":"15","bottom":"30","left":"0","isLinked":false},"_inline_size_tablet":100,"margin_tablet":{"unit":"px","top":"0","right":"0","bottom":"30","left":"0","isLinked":false},"padding_tablet":{"unit":"px","top":"0","right":"0","bottom":"0","left":"0","isLinked":false}},"elements":[{"id":"56b0c770","settings":{"bg_img_source":"external_link","bg_img_link":{"url":"https:\/\/ciyashop.potenzaglobalsolutions.com\/fashion-vintage\/wp-content\/uploads\/sites\/29\/2018\/08\/wild-img.jpg","is_external":false,"nofollow":false,"custom_attributes":""},"vertical_align":"vmiddle","horizontal_align":"hcenter","banner_effect":"flash","banner_css":{"unit":"px","top":"25","right":"25","bottom":"25","left":"25","isLinked":false},"banner_enable_button":"yes","list_items":[{"title":"Wild & Free","_id":"6dd3688","color":"#FFFFFF","item_typography_typography":"custom","item_typography_font_family":"Abril Fatface","item_typography_font_size":{"unit":"px","size":63,"sizes":[]},"item_typography_font_weight":"400","item_typography_line_height":{"unit":"px","size":66,"sizes":[]},"item_margin":{"unit":"px","top":"0","right":"0","bottom":"20","left":"0","isLinked":false},"item_typography_font_size_mobile":{"unit":"px","size":27,"sizes":[]},"item_typography_line_height_mobile":{"unit":"em","size":2,"sizes":[]}}],"button_text":"Shop now","button_style":"flat","button_typography_typography":"custom","button_typography_text_transform":"uppercase","button_text_color":"#1B1813","button_background_color":"#FFFFFF","badge_title":"Lorem Ipsum","deal_expire_message":"This offer has expired.","button_text_hover_color":"#FFFFFF","button_background_hover_color":"#BAA17D"},"elements":[],"isInner":false,"widgetType":"pgscore_banner","elType":"widget"}],"isInner":true,"elType":"column"},{"id":"1ecc4cbe","settings":{"_column_size":50,"_inline_size":null,"padding":{"unit":"px","top":"0","right":"0","bottom":"0","left":"15","isLinked":false},"_inline_size_tablet":100,"padding_tablet":{"unit":"px","top":"0","right":"0","bottom":"0","left":"0","isLinked":false}},"elements":[{"id":"5404925","settings":{"listing_type":"carousel","link_title":"View All","list_carousel_items_md":"2","list_carousel_items_lg":"2","list_carousel_items_xl":"2"},"elements":[],"isInner":false,"widgetType":"pgscore_product-listing","elType":"widget"}],"isInner":true,"elType":"column"}],"isInner":true,"elType":"section"}],"isInner":false,"elType":"column"}],"isInner":false,"elType":"section"}],"page_settings":[],"version":"0.4","title":"vSZAas","type":"section"}